ORCID_Hub-4.16.0.data/data/instance/README.md
ORCID_Hub-4.16.0.data/data/instance/settings.sample.cfg
ORCID_Hub-4.16.0.data/data/schemas/funding_schema.yaml
ORCID_Hub-4.16.0.data/data/schemas/orcid_swagger.json
ORCID_Hub-4.16.0.data/data/schemas/peer_review_schema.yaml
ORCID_Hub-4.16.0.data/data/schemas/work_schema.yaml
orcid_api/README.md
orcid_api/__init__.py
orcid_api/api_client.py
orcid_api/configuration.py
orcid_api/rest.py
orcid_api/apis/__init__.py
orcid_api/apis/development_member_apiv30_dev1_api.py
orcid_api/apis/member_apiv20_api.py
orcid_api/apis/member_apiv21_api.py
orcid_api/docs/ActivitiesSummary.md
orcid_api/docs/Address.md
orcid_api/docs/Amount.md
orcid_api/docs/AuthorizationUrl.md
orcid_api/docs/BulkElement.md
orcid_api/docs/Citation.md
orcid_api/docs/Contributor.md
orcid_api/docs/ContributorAttributes.md
orcid_api/docs/ContributorEmail.md
orcid_api/docs/ContributorOrcid.md
orcid_api/docs/Country.md
orcid_api/docs/CreatedDate.md
orcid_api/docs/CreditName.md
orcid_api/docs/Day.md
orcid_api/docs/DisambiguatedOrganization.md
orcid_api/docs/Education.md
orcid_api/docs/EducationSummary.md
orcid_api/docs/Educations.md
orcid_api/docs/Employment.md
orcid_api/docs/EmploymentSummary.md
orcid_api/docs/Employments.md
orcid_api/docs/ExternalID.md
orcid_api/docs/ExternalIDs.md
orcid_api/docs/Funding.md
orcid_api/docs/FundingContributor.md
orcid_api/docs/FundingContributorAttributes.md
orcid_api/docs/FundingContributors.md
orcid_api/docs/FundingGroup.md
orcid_api/docs/FundingSummary.md
orcid_api/docs/FundingTitle.md
orcid_api/docs/Fundings.md
orcid_api/docs/FuzzyDate.md
orcid_api/docs/GroupIdRecord.md
orcid_api/docs/GroupIdRecords.md
orcid_api/docs/Item.md
orcid_api/docs/Items.md
orcid_api/docs/Keyword.md
orcid_api/docs/LastModifiedDate.md
orcid_api/docs/MemberAPIV20Api.md
orcid_api/docs/MemberAPIV21Api.md
orcid_api/docs/Month.md
orcid_api/docs/Notification.md
orcid_api/docs/NotificationPermission.md
orcid_api/docs/Organization.md
ORCID_Hub-4.16.0.dist-info/AUTHORS
ORCID_Hub-4.16.0.dist-info/LICENSE
ORCID_Hub-4.16.0.dist-info/METADATA
ORCID_Hub-4.16.0.dist-info/WHEEL
ORCID_Hub-4.16.0.dist-info/dependency_links.txt
ORCID_Hub-4.16.0.dist-info/entry_points.txt
ORCID_Hub-4.16.0.dist-info/pbr.json
ORCID_Hub-4.16.0.dist-info/top_level.txt
ORCID_Hub-4.16.0.dist-info/RECORD
