Metadata-Version: 2.1
Name: ORCID-Hub
Version: 4.16.0
Summary: New Zealand ORCID Hub (Federated ORCID Intergration Solution for New Zealand ORCID Consortium)
Home-page: https://github.com/Royal-Society-of-New-Zealand/NZ-ORCID-Hub/
Author: Jason Gush, Radomirs Cirskis, Roshan Pawar
Author-email: jagu04@gmail.com, nad2000@gmail.com, roshan.pawar@auckland.ac.nz
License: MIT
Project-URL: Bug Tracker, https://goo.gl/vcPXK4
Project-URL: Documentation, http://docs.orcidhub.org.nz/
Project-URL: Source Code, https://github.com/Royal-Society-of-New-Zealand/NZ-ORCID-Hub/
Keywords: orcid
Requires-Dist: oauthlib (==2.1.0)
Requires-Dist: requests
Requires-Dist: requests-oauthlib (==1.0.0)
Requires-Dist: psycopg2-binary
Requires-Dist: peewee (<3.0.0,>=2.10.0)
Requires-Dist: peewee-validates
Requires-Dist: python-slugify
Requires-Dist: emails
Requires-Dist: wtf-peewee (==0.2.6)
Requires-Dist: pycountry
Requires-Dist: html2text
Requires-Dist: tablib
Requires-Dist: openpyxl (<2.5.0,>=2.4.9)
Requires-Dist: pyyaml
Requires-Dist: pykwalify
Requires-Dist: Flask
Requires-Dist: flask-admin
Requires-Dist: flask-login
Requires-Dist: Flask-WTF
Requires-Dist: flask-peewee (==0.6.7)
Requires-Dist: Flask-OAuthlib (==0.9.5)
Requires-Dist: raven[flask]
Requires-Dist: sentry-sdk[flask]
Requires-Dist: flask-peewee-swagger (>=1.1.5)
Requires-Dist: flask-limiter (<2.0.0,>=1.0.0)
Requires-Dist: flask-swagger
Requires-Dist: flask-restful
Requires-Dist: jsonschema (<3.0.0,>=2.6.0)
Requires-Dist: validators
Requires-Dist: croniter (==0.3.20)
Requires-Dist: redis (<4.0.0)
Requires-Dist: rq (<0.14.0)
Requires-Dist: rq-scheduler (<0.10)
Requires-Dist: Flask-RQ2[cli] (<19.0)
Requires-Dist: rq-dashboard (<0.5.0)
Requires-Dist: zipstream
Provides-Extra: dev
Requires-Dist: sphinx ; extra == 'dev'
Requires-Dist: sphinx-autobuild ; extra == 'dev'
Requires-Dist: m2r ; extra == 'dev'
Requires-Dist: recommonmark ; extra == 'dev'
Requires-Dist: pyyaml ; extra == 'dev'
Requires-Dist: coverage (>=4.4.1) ; extra == 'dev'
Requires-Dist: coveralls (>=1.2.0) ; extra == 'dev'
Requires-Dist: flake8 (>=3.4.1) ; extra == 'dev'
Requires-Dist: flake8-docstrings (>=1.1.0) ; extra == 'dev'
Requires-Dist: flake8-polyfill (>=1.0.1) ; extra == 'dev'
Requires-Dist: flask-debugtoolbar (>=0.10.1) ; extra == 'dev'
Requires-Dist: isort (>=4.2.15) ; extra == 'dev'
Requires-Dist: mccabe (>=0.6.1) ; extra == 'dev'
Requires-Dist: pep8-naming (>=0.4.1) ; extra == 'dev'
Requires-Dist: pydocs (>=0.2) ; extra == 'dev'
Requires-Dist: pydocstyle (>=2.0.0) ; extra == 'dev'
Requires-Dist: Pygments (>=2.2.0) ; extra == 'dev'
Requires-Dist: pytest (<3.7.0) ; extra == 'dev'
Requires-Dist: pytest-cov (>=2.5.1) ; extra == 'dev'
Requires-Dist: pytest-mock ; extra == 'dev'
Requires-Dist: testpath (>=0.3.1) ; extra == 'dev'
Requires-Dist: yapf (>=0.17.0) ; extra == 'dev'
Requires-Dist: pycrypto (>=2.6.1) ; extra == 'dev'
Requires-Dist: Faker ; extra == 'dev'
Requires-Dist: beautifulsoup4 ; extra == 'dev'
Provides-Extra: test
Requires-Dist: pyyaml ; extra == 'test'
Requires-Dist: coverage (>=4.4.1) ; extra == 'test'
Requires-Dist: coveralls (>=1.2.0) ; extra == 'test'
Requires-Dist: flake8 (>=3.4.1) ; extra == 'test'
Requires-Dist: flake8-docstrings (>=1.1.0) ; extra == 'test'
Requires-Dist: flake8-polyfill (>=1.0.1) ; extra == 'test'
Requires-Dist: mccabe (>=0.6.1) ; extra == 'test'
Requires-Dist: pep8-naming (>=0.4.1) ; extra == 'test'
Requires-Dist: pydocs (>=0.2) ; extra == 'test'
Requires-Dist: pytest (<3.7.0) ; extra == 'test'
Requires-Dist: pytest-cov (>=2.5.1) ; extra == 'test'
Requires-Dist: pytest-mock ; extra == 'test'
Requires-Dist: testpath (>=0.3.1) ; extra == 'test'
Requires-Dist: Faker ; extra == 'test'
Requires-Dist: Online-W3C-Validator (>=0.3.2) ; extra == 'test'
Requires-Dist: beautifulsoup4 ; extra == 'test'
